db_connector_tool/__about__.py
db_connector_tool/__init__.py
db_connector_tool/cli.py
db_connector_tool/core/__init__.py
db_connector_tool/core/config.py
db_connector_tool/core/connections.py
db_connector_tool/core/crypto.py
db_connector_tool/core/exceptions.py
db_connector_tool/drivers/__init__.py
db_connector_tool/drivers/gbase8s_jdbc.py
db_connector_tool/drivers/sqlalchemy_driver.py
db_connector_tool/utils/__init__.py
db_connector_tool/utils/logging_utils.py
db_connector_tool/utils/path_utils.py
db_connector_tool-0.2.0.dist-info/METADATA
db_connector_tool-0.2.0.dist-info/WHEEL
db_connector_tool-0.2.0.dist-info/entry_points.txt
db_connector_tool-0.2.0.dist-info/licenses/LICENSE.txt
db_connector_tool-0.2.0.dist-info/RECORD
