Metadata-Version: 2.4
Name: db-connector-tool
Version: 0.2.0
Summary: 跨平台数据库连接管理工具，支持多种数据库类型（Oracle, PostgreSQL, SQL Server, MySQL, SQLite, GBase8s）
Project-URL: Homepage, https://github.com/wangquanqing/db-connector-tool
Project-URL: Documentation, https://github.com/wangquanqing/db-connector-tool#readme
Project-URL: Issues, https://github.com/wangquanqing/db-connector-tool/issues
Project-URL: Source, https://github.com/wangquanqing/db-connector-tool
Author: wangquanqing
Author-email: wangquanqing1636@sina.com
License-Expression: MIT
License-File: LICENSE.txt
Keywords: connector,database,gbase8s,mysql,oracle,postgresql,sqlalchemy,sqlite,sqlserver
Classifier: Development Status :: 4 - Beta
Classifier: Intended Audience :: Developers
Classifier: License :: OSI Approved :: MIT License
Classifier: Programming Language :: Python
Classifier: Programming Language :: Python :: 3.8
Classifier: Programming Language :: Python :: 3.9
Classifier: Programming Language :: Python :: 3.10
Classifier: Programming Language :: Python :: 3.11
Classifier: Programming Language :: Python :: 3.12
Classifier: Programming Language :: Python :: Implementation :: CPython
Classifier: Programming Language :: Python :: Implementation :: PyPy
Classifier: Topic :: Database
Requires-Python: >=3.8
Requires-Dist: cryptography>=46.0.0
Requires-Dist: sqlalchemy>=2.0.0
Requires-Dist: tomli-w>=1.0.0
Provides-Extra: all
Requires-Dist: jaydebeapi<2,>=1.2.3; extra == 'all'
Requires-Dist: jpype1==1.5.2; extra == 'all'
Requires-Dist: oracledb>=3.0.0; extra == 'all'
Requires-Dist: psycopg>=3.0.0; extra == 'all'
Requires-Dist: pymssql>=2.0.0; extra == 'all'
Requires-Dist: pymysql>=1.0.0; extra == 'all'
Requires-Dist: python-dateutil<3,>=2.8.0; extra == 'all'
Provides-Extra: dev
Requires-Dist: black>=23.0.0; extra == 'dev'
Requires-Dist: isort>=5.12.0; extra == 'dev'
Requires-Dist: pyright>=1.0.0; extra == 'dev'
Requires-Dist: pytest-cov>=4.0.0; extra == 'dev'
Requires-Dist: pytest>=7.0.0; extra == 'dev'
Provides-Extra: gbase8s
Requires-Dist: jaydebeapi<2,>=1.2.3; extra == 'gbase8s'
Requires-Dist: jpype1==1.5.2; extra == 'gbase8s'
Requires-Dist: python-dateutil<3,>=2.8.0; extra == 'gbase8s'
Provides-Extra: mysql
Requires-Dist: pymysql>=1.0.0; extra == 'mysql'
Provides-Extra: oracle
Requires-Dist: oracledb>=3.0.0; extra == 'oracle'
Provides-Extra: postgresql
Requires-Dist: psycopg>=3.0.0; extra == 'postgresql'
Provides-Extra: sqlserver
Requires-Dist: pymssql>=2.0.0; extra == 'sqlserver'
